odoo10_addon_subcontracted_service-10.0.2.0.0-py2.7-nspkg.pth
odoo/addons/subcontracted_service/README.rst
odoo/addons/subcontracted_service/__init__.py
odoo/addons/subcontracted_service/__manifest__.py
odoo/addons/subcontracted_service/init_hook.py
odoo/addons/subcontracted_service/i18n/ca.po
odoo/addons/subcontracted_service/i18n/de.po
odoo/addons/subcontracted_service/i18n/el_GR.po
odoo/addons/subcontracted_service/i18n/es.po
odoo/addons/subcontracted_service/i18n/es_PE.po
odoo/addons/subcontracted_service/i18n/fi.po
odoo/addons/subcontracted_service/i18n/fr.po
odoo/addons/subcontracted_service/i18n/fr_FR.po
odoo/addons/subcontracted_service/i18n/gl.po
odoo/addons/subcontracted_service/i18n/hr.po
odoo/addons/subcontracted_service/i18n/hr_HR.po
odoo/addons/subcontracted_service/i18n/it.po
odoo/addons/subcontracted_service/i18n/nl.po
odoo/addons/subcontracted_service/i18n/nl_NL.po
odoo/addons/subcontracted_service/i18n/pt.po
odoo/addons/subcontracted_service/i18n/pt_BR.po
odoo/addons/subcontracted_service/i18n/ro.po
odoo/addons/subcontracted_service/i18n/sl.po
odoo/addons/subcontracted_service/i18n/subcontracted_service.pot
odoo/addons/subcontracted_service/i18n/vi_VN.po
odoo/addons/subcontracted_service/i18n/zh_CN.po
odoo/addons/subcontracted_service/migrations/10.0.2.0.0/pre-migration.py
odoo/addons/subcontracted_service/models/__init__.py
odoo/addons/subcontracted_service/models/procurement.py
odoo/addons/subcontracted_service/models/product.py
odoo/addons/subcontracted_service/models/warehouse.py
odoo/addons/subcontracted_service/static/description/icon.png
odoo/addons/subcontracted_service/tests/__init__.py
odoo/addons/subcontracted_service/tests/test_subcontracted_service.py
odoo/addons/subcontracted_service/views/product_template.xml
odoo/addons/subcontracted_service/views/warehouse.xml
odoo10_addon_subcontracted_service-10.0.2.0.0.dist-info/METADATA
odoo10_addon_subcontracted_service-10.0.2.0.0.dist-info/RECORD
odoo10_addon_subcontracted_service-10.0.2.0.0.dist-info/WHEEL
odoo10_addon_subcontracted_service-10.0.2.0.0.dist-info/namespace_packages.txt
odoo10_addon_subcontracted_service-10.0.2.0.0.dist-info/top_level.txt
